photoshop_object_model_session/__init__.py
photoshop_object_model_session/session.py
photoshop_object_model_session-0.0.2.dist-info/LICENSE
photoshop_object_model_session-0.0.2.dist-info/METADATA
photoshop_object_model_session-0.0.2.dist-info/WHEEL
photoshop_object_model_session-0.0.2.dist-info/top_level.txt
photoshop_object_model_session-0.0.2.dist-info/RECORD
