Metadata-Version: 2.1
Name: photoshop-object-model-session
Version: 0.0.2
Summary: Photoshop Object Model Session
Author: Tristan Languebien
Author-email: <tlanguebien@gmail.com>
Keywords: python,photoshop
Classifier: Development Status :: 1 - Planning
Classifier: Intended Audience :: Developers
Classifier: Programming Language :: Python :: 3
Classifier: Operating System :: Microsoft :: Windows
License-File: LICENSE
Requires-Dist: pywin32
Requires-Dist: photoshop-object-model
